duck_dataset/__init__.py
duck_dataset/aggregations.py
duck_dataset/main.py
duck_dataset-0.2.0.dist-info/METADATA
duck_dataset-0.2.0.dist-info/WHEEL
duck_dataset-0.2.0.dist-info/RECORD
